libretranslate_euber/__init__.py
libretranslate_euber/api_keys.py
libretranslate_euber/app.py
libretranslate_euber/default_values.py
libretranslate_euber/flood.py
libretranslate_euber/init.py
libretranslate_euber/language.py
libretranslate_euber/main.py
libretranslate_euber/manage.py
libretranslate_euber/no_limiter.py
libretranslate_euber/static/css/main.css
libretranslate_euber/static/css/material-icons.css
libretranslate_euber/static/css/materialize.min.css
libretranslate_euber/static/css/prism.min.css
libretranslate_euber/static/favicon.ico
libretranslate_euber/static/fonts/MaterialIcons-Regular.eot
libretranslate_euber/static/fonts/MaterialIcons-Regular.ttf
libretranslate_euber/static/fonts/MaterialIcons-Regular.woff
libretranslate_euber/static/fonts/MaterialIcons-Regular.woff2
libretranslate_euber/static/icon.svg
libretranslate_euber/static/js/materialize.min.js
libretranslate_euber/static/js/prism.min.js
libretranslate_euber/static/js/vue@2.js
libretranslate_euber/templates/index.html
libretranslate_euber/templates/javascript-licenses.html
libretranslate_euber-0.1.0.dist-info/entry_points.txt
libretranslate_euber-0.1.0.dist-info/LICENSE
libretranslate_euber-0.1.0.dist-info/WHEEL
libretranslate_euber-0.1.0.dist-info/METADATA
libretranslate_euber-0.1.0.dist-info/RECORD
