Metadata-Version: 2.1
Name: libretranslate-euber
Version: 0.1.0
Summary: My personal porting of libretranslate
License: GPL
Author: euberdeveloper
Author-email: euberdeveloper@gmail.com
Requires-Python: >=3.8,<4.0
Classifier: License :: Other/Proprietary License
Classifier: Programming Language :: Python :: 3
Classifier: Programming Language :: Python :: 3.8
Classifier: Programming Language :: Python :: 3.9
Requires-Dist: APScheduler (>=3.7.0,<4.0.0)
Requires-Dist: Flask (>=2.0.1,<3.0.0)
Requires-Dist: Flask-Limiter (>=1.4,<2.0)
Requires-Dist: Morfessor (>=2.0.6,<3.0.0)
Requires-Dist: PyICU (>=2.7.4,<3.0.0)
Requires-Dist: appdirs (>=1.4.4,<2.0.0)
Requires-Dist: argostranslate (>=1.4.0,<2.0.0)
Requires-Dist: expiringdict (>=1.2.1,<2.0.0)
Requires-Dist: flask-swagger (>=0.2.14,<0.3.0)
Requires-Dist: flask-swagger-ui (>=3.36.0,<4.0.0)
Requires-Dist: polyglot (>=16.7.4,<17.0.0)
Requires-Dist: pycld2 (>=0.41,<0.42)
Requires-Dist: pysqlite3 (>=0.4.6,<0.5.0)
Requires-Dist: waitress (>=2.0.0,<3.0.0)
